{
  "$schema": "https://schema.tauri.app/config/2",
  "productName": "game-grove",
  "identifier": "com.mxstbr.game-grove",
  "build": {
    "beforeDevCommand": "pnpm dev",
    "devUrl": "http://localhost:1420",
    "beforeBuildCommand": "pnpm build",
    "frontendDist": "../dist"
  },
  "app": {
    "windows": [
      {
        "title": "game-grove",
        "width": 800,
        "height": 600
      }
    ],
    "security": {
      "csp": null
    },
    "macOSPrivateApi": true
  },
  "bundle": {
    "active": true,
    "targets": "all",
    "createUpdaterArtifacts": true,
    "icon": [
      "icons/32x32.png",
      "icons/128x128.png",
      "icons/128x128@2x.png",
      "icons/icon.icns",
      "icons/icon.ico"
    ]
  },
  "plugins": {
    "updater": {
      "endpoints": [
        "https://github.com/mxstbr/game-grove/releases/latest/download/latest.json"
      ],
      "dialog": true,
      "pubkey": "dW50cnVzdGVkIGNvbW1lbnQ6IG1pbmlzaWduIHB1YmxpYyBrZXk6IDU5RUI1NEQ2QTU0N0FFMkMKUldRc3JrZWwxbFRyV2ZsTTg1dFA0T1duTHBSd210WXlOejUwU3NhdEhCcDVQVFA1WFQvZXJNM0IK"
    }
  }
}
